pystm32ai/__init__.py
pystm32ai/stm32ai.py
pystm32ai-1.0.1.dist-info/METADATA
pystm32ai-1.0.1.dist-info/WHEEL
pystm32ai-1.0.1.dist-info/entry_points.txt
pystm32ai-1.0.1.dist-info/licenses/LICENSE.txt
pystm32ai-1.0.1.dist-info/RECORD
