Metadata-Version: 2.4
Name: pystm32ai
Version: 1.0.1
Summary: Python Wrapper for stedgeai command line tool
Project-URL: repository, https://github.com/thibthibaut/pystm32ai
Author-email: Thibaut VERCUEIL <thibaut.vercueil@pm.me>
License: MIT
License-File: LICENSE.txt
Requires-Python: >=3.8
Requires-Dist: py7zr>=0.22.0
Requires-Dist: requests>=2.27.1
Requires-Dist: rich>=13.9.4
Requires-Dist: tqdm>=4.62.3
Provides-Extra: dev
Requires-Dist: pylint>=2.12.2; extra == 'dev'
Requires-Dist: pytest>=5.2; extra == 'dev'
Requires-Dist: ruff>=0.9.0; extra == 'dev'
